pyau/__init__.py
pyau-0.2.0.dist-info/METADATA
pyau-0.2.0.dist-info/WHEEL
pyau-0.2.0.dist-info/RECORD
