Metadata-Version: 2.4
Name: pyau
Version: 0.2.0
Summary: A Python library mimicking Luau.
Author: nahhkandy
License: MIT
Requires-Python: >=3.7
